abspasschek-0.1.0.dist-info/licenses/LICENSE
mycheckpkg/__init__.py
mycheckpkg/checker.py
abspasschek-0.1.0.dist-info/METADATA
abspasschek-0.1.0.dist-info/WHEEL
abspasschek-0.1.0.dist-info/entry_points.txt
abspasschek-0.1.0.dist-info/top_level.txt
abspasschek-0.1.0.dist-info/RECORD
